{"dependencies":[{"name":"./../js/index.js","dynamic":true}],"generated":{"html":"<!DOCTYPE html>\n<html lang=\"ja\">\n  <head>\n    <meta charset=\"UTF-8\"/>\n    <meta http-equiv=\"X-UA-Compatible\" content=\"IE=edge\"/>\n    <meta name=\"viewport\" content=\"width=device-width,initial-scale=1\"/>\n    <title>parcel sample moc</title>\n  </head>\n  <body>\n    <div class=\"container\">\n      <h1>parcel sample.</h1>\n      <p>using pug ,scss, and postcss(autoprefixer).</p>\n    </div>\n    <script src=\"/dist/53c74396470b0a7d689cc6c7334720ab.js\"></script>\n  </body>\n</html>"},"hash":"7d1f43471ea009e6fb23dd04ec2836c8"}